soundchartspy/__about__.py
soundchartspy/__init__.py
soundchartspy/client.py
soundchartspy/data.py
soundchartspy/exceptions.py
soundchartspy/utils.py
soundchartspy-0.1.4.dist-info/METADATA
soundchartspy-0.1.4.dist-info/WHEEL
soundchartspy-0.1.4.dist-info/licenses/LICENSE
soundchartspy-0.1.4.dist-info/RECORD
