Metadata-Version: 2.3
Name: soundchartspy
Version: 0.1.4
Summary: A python wrapper package for the paid api from SoundCharts. This package is not affiliated with soundcharts and is not endorsed by them. However, it is built upon their api and can be used assuming you have a paid subscription to their service.
Project-URL: Homepage, https://github.com/AidanAlr/soundchartspy
Project-URL: Issues, https://github.com/AidanAlr/soundchartspy/issues
Author-email: AidanAlr <aidanalrawi@icloud.com>
License-File: LICENSE
Classifier: License :: OSI Approved :: MIT License
Classifier: Operating System :: OS Independent
Classifier: Programming Language :: Python :: 3
Requires-Python: >=3.8
Requires-Dist: requests
Provides-Extra: dev
Requires-Dist: flake8; extra == 'dev'
Requires-Dist: pytest; extra == 'dev'
